cli/cli.py
cli/manifest.toml
opsbox_cli_output-0.2.1.dist-info/LICENSE.txt
opsbox_cli_output-0.2.1.dist-info/METADATA
opsbox_cli_output-0.2.1.dist-info/WHEEL
opsbox_cli_output-0.2.1.dist-info/entry_points.txt
opsbox_cli_output-0.2.1.dist-info/top_level.txt
opsbox_cli_output-0.2.1.dist-info/RECORD
