Metadata-Version: 2.2
Name: opsbox-cli-output
Version: 0.2.1
Summary: Command-line output for opsbox
License: Mozilla Public License Version 2.0
Requires-Python: ==3.11.*
License-File: LICENSE.txt
Requires-Dist: loguru>=0.7.2
Requires-Dist: pluggy>=1.5.0
Requires-Dist: opsbox-general-handler>=0.1.2
